README.rst
setup.py
hexagonit/__init__.py
hexagonit.testing.egg-info/PKG-INFO
hexagonit.testing.egg-info/SOURCES.txt
hexagonit.testing.egg-info/dependency_links.txt
hexagonit.testing.egg-info/entry_points.txt
hexagonit.testing.egg-info/namespace_packages.txt
hexagonit.testing.egg-info/not-zip-safe
hexagonit.testing.egg-info/requires.txt
hexagonit.testing.egg-info/top_level.txt
hexagonit/testing/__init__.py
hexagonit/testing/browser.py
hexagonit/testing/date.py
hexagonit/testing/mech.py
hexagonit/testing/mime.py
hexagonit/testing/docs/CONTRIBUTORS.rst
hexagonit/testing/docs/HISTORY.rst
hexagonit/testing/docs/INSTALL.rst
hexagonit/testing/docs/LICENSE.rst
hexagonit/testing/docs/Makefile
hexagonit/testing/docs/README.rst
hexagonit/testing/docs/conf.py
hexagonit/testing/docs/index.rst
hexagonit/testing/tests/__init__.py
hexagonit/testing/tests/base.py
hexagonit/testing/tests/test_browser.py
hexagonit/testing/tests/test_date.py
hexagonit/testing/tests/test_datetime.py
hexagonit/testing/tests/test_functional.py
hexagonit/testing/tests/test_mechanize.py
hexagonit/testing/tests/test_mime.py
hexagonit/testing/tests/browser/__init__.py
hexagonit/testing/tests/browser/configure.zcml
hexagonit/testing/tests/browser/template.py
hexagonit/testing/tests/browser/templates/test_form.pt
hexagonit/testing/tests/functional/browser.txt