Metadata-Version: 1.0
Name: hexagonit.testing
Version: 1.2.1
Summary: Plone4 test helper which uses plone.testing and manuel.
Home-page: http://packages.python.org/hexagonit.testing/
Author: Hexagon IT
Author-email: oss@hexagonit.fi
License: BSD
Platform: UNKNOWN
Classifier: Framework :: Plone
Classifier: Framework :: Plone :: 4.1
Classifier: Framework :: Plone :: 4.2
Classifier: Framework :: Plone :: 4.3
Classifier: Programming Language :: Python
